mdaviz/__init__.py
mdaviz/aboutdialog.py
mdaviz/app.py
mdaviz/chartview.py
mdaviz/data_cache.py
mdaviz/data_table_model.py
mdaviz/data_table_view.py
mdaviz/empty_table_model.py
mdaviz/fit_manager.py
mdaviz/fit_models.py
mdaviz/lazy_folder_scanner.py
mdaviz/lazy_loading_config.py
mdaviz/licensedialog.py
mdaviz/logger.py
mdaviz/logging_config.py
mdaviz/mainwindow.py
mdaviz/mda_file.py
mdaviz/mda_file_table_model.py
mdaviz/mda_file_table_view.py
mdaviz/mda_file_viz.py
mdaviz/mda_folder.py
mdaviz/mda_folder_table_model.py
mdaviz/mda_folder_table_view.py
mdaviz/multidimensional_data_table_model.py
mdaviz/opendialog.py
mdaviz/popup.py
mdaviz/progress_dialog.py
mdaviz/py.typed
mdaviz/user_settings.py
mdaviz/utils.py
mdaviz/virtual_table_model.py
mdaviz/resources/aboutdialog.ui
mdaviz/resources/apply.png
mdaviz/resources/back.png
mdaviz/resources/delete.png
mdaviz/resources/first.png
mdaviz/resources/first.png.png
mdaviz/resources/first.svg
mdaviz/resources/icons.pptx
mdaviz/resources/last.png
mdaviz/resources/last.svg
mdaviz/resources/licensedialog.ui
mdaviz/resources/mainwindow.ui
mdaviz/resources/mda_file.ui
mdaviz/resources/mda_file_table_view.ui
mdaviz/resources/mda_file_viz.ui
mdaviz/resources/mda_folder.ui
mdaviz/resources/mda_folder_table_view.ui
mdaviz/resources/next.png
mdaviz/resources/open.png
mdaviz/resources/open.svg
mdaviz/resources/plus.png
mdaviz/resources/popup.ui
mdaviz/resources/refresh.png
mdaviz/resources/select_fields_table_view.ui
mdaviz/resources/set.png
mdaviz/resources/viz.png
mdaviz/synApps_mdalib/METADATA
mdaviz/synApps_mdalib/README.md
mdaviz/synApps_mdalib/__init__.py
mdaviz/synApps_mdalib/f_xdrlib.py
mdaviz/synApps_mdalib/mda.py
mdaviz-1.2.5.dist-info/licenses/LICENSE.txt
mdaviz-1.2.5.dist-info/METADATA
mdaviz-1.2.5.dist-info/WHEEL
mdaviz-1.2.5.dist-info/entry_points.txt
mdaviz-1.2.5.dist-info/top_level.txt
mdaviz-1.2.5.dist-info/RECORD
