Metadata-Version: 2.4
Name: mdaviz
Version: 1.2.5
Summary: Python Qt6 application to visualize multi-dimensional arrays (MDA) files from synchrotron beamlines.
Author-email: Fanny Rodolakis <rodolakis@anl.gov>, Pete Jemian <prjemian@gmail.com>, Rafael Vescovi <ravescovi@anl.gov>, Eric Codrea <ecodrea@anl.gov>
Maintainer-email: Fanny Rodolakis <rodolakis@anl.gov>, Pete Jemian <prjemian@gmail.com>, Rafael Vescovi <ravescovi@anl.gov>, Eric Codrea <ecodrea@anl.gov>
Project-URL: Homepage, https://github.com/BCDA-APS/mdaviz
Project-URL: Bug Tracker, https://github.com/BCDA-APS/mdaviz/issues
Keywords: mda,multidimensional-data,visualization,synchrotron,beamline,EPICS
Classifier: Development Status :: 4 - Beta
Classifier: Environment :: Console
Classifier: Intended Audience :: Science/Research
Classifier: License :: Freely Distributable
Classifier: License :: Public Domain
Classifier: Operating System :: OS Independent
Classifier: Programming Language :: Python :: 3
Classifier: Programming Language :: Python
Classifier: Topic :: Scientific/Engineering :: Astronomy
Classifier: Topic :: Scientific/Engineering :: Bio-Informatics
Classifier: Topic :: Scientific/Engineering :: Chemistry
Classifier: Topic :: Scientific/Engineering :: Mathematics
Classifier: Topic :: Scientific/Engineering :: Physics
Classifier: Topic :: Scientific/Engineering :: Visualization
Classifier: Topic :: Scientific/Engineering
Classifier: Topic :: Utilities
Classifier: Programming Language :: Python :: 3.10
Classifier: Programming Language :: Python :: 3.11
Classifier: Programming Language :: Python :: 3.12
Classifier: Programming Language :: Python :: 3.13
Requires-Python: <3.14,>=3.10
License-File: LICENSE.txt
Requires-Dist: matplotlib>=3.8.0
Requires-Dist: PyQt6>=6.6.0
Requires-Dist: PyYAML>=6.0.1
Requires-Dist: scipy>=1.12.0
Requires-Dist: lmfit>=1.3.0
Requires-Dist: psutil>=5.9.0
Provides-Extra: dev
Requires-Dist: pytest>=7.0; extra == "dev"
Requires-Dist: pytest-cov>=4.0; extra == "dev"
Requires-Dist: ruff>=0.1.0; extra == "dev"
Requires-Dist: mypy>=1.0; extra == "dev"
Requires-Dist: pre-commit>=3.0; extra == "dev"
Requires-Dist: types-PyYAML; extra == "dev"
Requires-Dist: pytest-qt>=4.2.0; extra == "dev"
Provides-Extra: build
Requires-Dist: pyinstaller>=6.0.0; extra == "build"
Requires-Dist: cx_Freeze>=6.15.0; extra == "build"
Requires-Dist: nuitka>=1.8.0; extra == "build"
Dynamic: license-file
